skitai/Skitai.py
skitai/__init__.py
skitai/counter.py
skitai/exceptions.py
skitai/utility.py
skitai/backbone/__init__.py
skitai/backbone/http3_server.py
skitai/backbone/http_request.py
skitai/backbone/http_response.py
skitai/backbone/http_server.py
skitai/backbone/https_server.py
skitai/backbone/lifetime.py
skitai/backbone/threaded/__init__.py
skitai/backbone/threaded/select_trigger.py
skitai/backbone/threaded/socket_map.py
skitai/backbone/threaded/threadlib.py
skitai/backbone/threaded/trigger.py
skitai/backbone/threaded/trigger_file.py
skitai/handlers/__init__.py
skitai/handlers/collectors.py
skitai/handlers/default_handler.py
skitai/handlers/filesys.py
skitai/handlers/forward_handler.py
skitai/handlers/grpc_stream_handler.py
skitai/handlers/http2_handler.py
skitai/handlers/http3_handler.py
skitai/handlers/mime_type_table.py
skitai/handlers/pingpong_handler.py
skitai/handlers/vhost_handler.py
skitai/handlers/websocket_handler.py
skitai/handlers/wsgi_handler.py
skitai/handlers/http2/__init__.py
skitai/handlers/http2/request.py
skitai/handlers/http2/response.py
skitai/handlers/http2/vchannel.py
skitai/handlers/websocket/__init__.py
skitai/handlers/websocket/specs.py
skitai/handlers/websocket/task_runner.py
skitai/mounted/__init__.py
skitai/scripts/__init__.py
skitai/scripts/skitai.py
skitai/scripts/commands/__init__.py
skitai/scripts/commands/init.py
skitai/scripts/commands/pstats.py
skitai/scripts/commands/smtpda.py
skitai/scripts/commands/status.py
skitai/tasks/__init__.py
skitai/tasks/derivations.py
skitai/tasks/executors.py
skitai/tasks/utils.py
skitai/tasks/pth/__init__.py
skitai/tasks/pth/sp_task.py
skitai/tasks/pth/task.py
skitai/testutil/__init__.py
skitai/testutil/launcher.py
skitai/testutil/offline/__init__.py
skitai/testutil/offline/client.py
skitai/testutil/offline/server.py
skitai/wastuff/__init__.py
skitai/wastuff/api.py
skitai/wastuff/autoconf.py
skitai/wastuff/django_reloader.py
skitai/wastuff/preference.py
skitai/wastuff/selective_logger.py
skitai-0.57.16.dist-info/licenses/LICENSE
skitai-0.57.16.dist-info/METADATA
skitai-0.57.16.dist-info/WHEEL
skitai-0.57.16.dist-info/entry_points.txt
skitai-0.57.16.dist-info/top_level.txt
skitai-0.57.16.dist-info/RECORD
