Metadata-Version: 2.4
Name: skitai
Version: 0.57.16
Summary: Skitai App Engine
Home-page: https://gitlab.com/skitai/skitai
Download-URL: https://pypi.python.org/pypi/skitai
Author: Hans Roh
Author-email: hansroh@gmail.com
License: MIT
Platform: posix
Platform: nt
Classifier: Development Status :: 4 - Beta
Classifier: Topic :: Internet :: WWW/HTTP :: WSGI
Classifier: Environment :: Console
Classifier: Environment :: No Input/Output (Daemon)
Classifier: Topic :: Internet
Classifier: Topic :: Software Development :: Libraries :: Python Modules
Classifier: Intended Audience :: Developers
Classifier: Programming Language :: Python :: 3.8
Classifier: Programming Language :: Python :: 3.9
Classifier: Programming Language :: Python :: 3.10
Classifier: Programming Language :: Python :: 3.11
Classifier: Programming Language :: Python :: 3.12
Classifier: Programming Language :: Python :: Implementation :: CPython
License-File: LICENSE
Requires-Dist: rs4>=0.3.30
Requires-Dist: sqlphile>=0.9
Requires-Dist: h2>=4.0.0
Dynamic: author
Dynamic: author-email
Dynamic: classifier
Dynamic: description
Dynamic: description-content-type
Dynamic: download-url
Dynamic: home-page
Dynamic: license
Dynamic: license-file
Dynamic: platform
Dynamic: requires-dist
Dynamic: summary
